{
  "name": "Khom",
  "sounds": [
    {
      "name": "02 Epsilon Base",
      "path": "assets/music/wueste/qwinff_output/02_Epsilon_Base.ogg",
      "_id": "LDaH2lsJWMCOqZIJ",
      "playing": false,
      "pausedTime": null,
      "repeat": false,
      "volume": 0.5,
      "fade": null,
      "sort": 0,
      "flags": {},
      "channel": "music",
      "_key": "!playlists.sounds!uxqHTJ8CQQ3qKQGb.LDaH2lsJWMCOqZIJ"
    },
    {
      "name": "03 Launch Of The Kapisi",
      "path": "assets/music/wueste/qwinff_output/03.%20Launch%20of%20The%20Kapisi.mp3",
      "_id": "TZGDx2KQBaMMmPFY",
      "playing": false,
      "pausedTime": null,
      "repeat": false,
      "volume": 0.5,
      "fade": null,
      "sort": 0,
      "flags": {},
      "channel": "music",
      "_key": "!playlists.sounds!uxqHTJ8CQQ3qKQGb.TZGDx2KQBaMMmPFY"
    },
    {
      "name": "06 Black Hawk Down Mogadishu Blues",
      "path": "assets/music/wueste/qwinff_output/06_Black_Hawk_Down___Mogadishu_Blues.ogg",
      "_id": "9X0TsTbqIoxmqQjr",
      "playing": false,
      "pausedTime": null,
      "repeat": false,
      "volume": 0.5,
      "fade": null,
      "sort": 0,
      "flags": {},
      "channel": "music",
      "_key": "!playlists.sounds!uxqHTJ8CQQ3qKQGb.9X0TsTbqIoxmqQjr"
    },
    {
      "name": "07 Battle At The Boneyard",
      "path": "assets/music/wueste/qwinff_output/07.%20Battle%20at%20The%20Boneyard.mp3",
      "_id": "o9bm6spuv7dxneQb",
      "playing": false,
      "pausedTime": null,
      "repeat": false,
      "volume": 0.5,
      "fade": null,
      "sort": 0,
      "flags": {},
      "channel": "music",
      "_key": "!playlists.sounds!uxqHTJ8CQQ3qKQGb.o9bm6spuv7dxneQb"
    },
    {
      "name": "100 Credits",
      "path": "assets/music/wueste/qwinff_output/100.%20Credits.mp3",
      "_id": "FZqupONtkymIpjqU",
      "playing": false,
      "pausedTime": null,
      "repeat": false,
      "volume": 0.5,
      "fade": null,
      "sort": 0,
      "flags": {},
      "channel": "music",
      "_key": "!playlists.sounds!uxqHTJ8CQQ3qKQGb.FZqupONtkymIpjqU"
    },
    {
      "name": "10 Black Hawk Down Ashes To Ashes",
      "path": "assets/music/wueste/qwinff_output/10_Black_Hawk_Down___Ashes_to_Ashes.ogg",
      "_id": "CHGx2Fc1mABY1AVg",
      "playing": false,
      "pausedTime": null,
      "repeat": false,
      "volume": 0.5,
      "fade": null,
      "sort": 0,
      "flags": {},
      "channel": "music",
      "_key": "!playlists.sounds!uxqHTJ8CQQ3qKQGb.CHGx2Fc1mABY1AVg"
    },
    {
      "name": "16 Hunted",
      "path": "assets/music/wueste/qwinff_output/16.%20Hunted.mp3",
      "_id": "K6WsqPl24ngjXi8U",
      "playing": false,
      "pausedTime": null,
      "repeat": false,
      "volume": 0.5,
      "fade": null,
      "sort": 0,
      "flags": {},
      "channel": "music",
      "_key": "!playlists.sounds!uxqHTJ8CQQ3qKQGb.K6WsqPl24ngjXi8U"
    },
    {
      "name": "20 Desert Sun Blz",
      "path": "assets/music/wueste/qwinff_output/20_desert_sun_blz.ogg",
      "_id": "qbbSGgbUfeURJBuy",
      "playing": false,
      "pausedTime": null,
      "repeat": false,
      "volume": 0.5,
      "fade": null,
      "sort": 0,
      "flags": {},
      "channel": "music",
      "_key": "!playlists.sounds!uxqHTJ8CQQ3qKQGb.qbbSGgbUfeURJBuy"
    },
    {
      "name": "21 Rachel, Scout Up Ahead",
      "path": "assets/music/wueste/qwinff_output/21.%20Rachel%2C%20Scout%20up%20Ahead.mp3",
      "_id": "GR0lwSOI3TSUi2GP",
      "playing": false,
      "pausedTime": null,
      "repeat": false,
      "volume": 0.5,
      "fade": null,
      "sort": 0,
      "flags": {},
      "channel": "music",
      "_key": "!playlists.sounds!uxqHTJ8CQQ3qKQGb.GR0lwSOI3TSUi2GP"
    },
    {
      "name": "21 Welcome To Varant Blz",
      "path": "assets/music/wueste/qwinff_output/21_welcome_to_varant_blz.ogg",
      "_id": "KSQPt0EiDAOhohNI",
      "playing": false,
      "pausedTime": null,
      "repeat": false,
      "volume": 0.5,
      "fade": null,
      "sort": 0,
      "flags": {},
      "channel": "music",
      "_key": "!playlists.sounds!uxqHTJ8CQQ3qKQGb.KSQPt0EiDAOhohNI"
    },
    {
      "name": "23 Expand The Search To The Valley Below",
      "path": "assets/music/wueste/qwinff_output/23.%20Expand%20the%20Search%20to%20the%20Valley%20Below.mp3",
      "_id": "AJxVDvtYyF3SJasI",
      "playing": false,
      "pausedTime": null,
      "repeat": false,
      "volume": 0.5,
      "fade": null,
      "sort": 0,
      "flags": {},
      "channel": "music",
      "_key": "!playlists.sounds!uxqHTJ8CQQ3qKQGb.AJxVDvtYyF3SJasI"
    },
    {
      "name": "25 Gaalsi On Advance",
      "path": "assets/music/wueste/qwinff_output/25.%20Gaalsi%20on%20Advance.mp3",
      "_id": "zceGU2YEj8ifzH2l",
      "playing": false,
      "pausedTime": null,
      "repeat": false,
      "volume": 0.5,
      "fade": null,
      "sort": 0,
      "flags": {},
      "channel": "music",
      "_key": "!playlists.sounds!uxqHTJ8CQQ3qKQGb.zceGU2YEj8ifzH2l"
    },
    {
      "name": "25 Gaalsi On Advance",
      "path": "assets/music/wueste/qwinff_output/25__Gaalsi_on_Advance.ogg",
      "_id": "W0IOHVZFiVy5L9ht",
      "playing": false,
      "pausedTime": null,
      "repeat": false,
      "volume": 0.5,
      "fade": null,
      "sort": 0,
      "flags": {},
      "channel": "music",
      "_key": "!playlists.sounds!uxqHTJ8CQQ3qKQGb.W0IOHVZFiVy5L9ht"
    },
    {
      "name": "26 Wrecks In The Field",
      "path": "assets/music/wueste/qwinff_output/26.%20Wrecks%20in%20the%20Field.mp3",
      "_id": "TY5XKtRcNvz8Nz9b",
      "playing": false,
      "pausedTime": null,
      "repeat": false,
      "volume": 0.5,
      "fade": null,
      "sort": 0,
      "flags": {},
      "channel": "music",
      "_key": "!playlists.sounds!uxqHTJ8CQQ3qKQGb.TY5XKtRcNvz8Nz9b"
    },
    {
      "name": "27 Sarathi Basin",
      "path": "assets/music/wueste/qwinff_output/27.%20Sarathi%20Basin.mp3",
      "_id": "49i5oojtkMkMuCiv",
      "playing": false,
      "pausedTime": null,
      "repeat": false,
      "volume": 0.5,
      "fade": null,
      "sort": 0,
      "flags": {},
      "channel": "music",
      "_key": "!playlists.sounds!uxqHTJ8CQQ3qKQGb.49i5oojtkMkMuCiv"
    },
    {
      "name": "30 Atmospheric Penetration Followed By Ground Impact",
      "path": "assets/music/wueste/qwinff_output/30.%20Atmospheric%20Penetration%20followed%20by%20Ground%20Impact.mp3",
      "_id": "McSMi3YpHNgqw41d",
      "playing": false,
      "pausedTime": null,
      "repeat": false,
      "volume": 0.5,
      "fade": null,
      "sort": 0,
      "flags": {},
      "channel": "music",
      "_key": "!playlists.sounds!uxqHTJ8CQQ3qKQGb.McSMi3YpHNgqw41d"
    },
    {
      "name": "34 Engage The Ashoka's Fleet",
      "path": "assets/music/wueste/qwinff_output/34.%20Engage%20The%20Ashoka%27s%20Fleet.mp3",
      "_id": "gZsYlkSMOyeOF384",
      "playing": false,
      "pausedTime": null,
      "repeat": false,
      "volume": 0.5,
      "fade": null,
      "sort": 0,
      "flags": {},
      "channel": "music",
      "_key": "!playlists.sounds!uxqHTJ8CQQ3qKQGb.gZsYlkSMOyeOF384"
    },
    {
      "name": "36 The Coalition Join With The Sidiim",
      "path": "assets/music/wueste/qwinff_output/36__The_Coalition_Join_with_the_Sidiim.ogg",
      "_id": "F6Be6tO630CwhKD2",
      "playing": false,
      "pausedTime": null,
      "repeat": false,
      "volume": 0.5,
      "fade": null,
      "sort": 0,
      "flags": {},
      "channel": "music",
      "_key": "!playlists.sounds!uxqHTJ8CQQ3qKQGb.F6Be6tO630CwhKD2"
    },
    {
      "name": "41 Gaalsi Resource Operation",
      "path": "assets/music/wueste/qwinff_output/41.%20Gaalsi%20Resource%20Operation.mp3",
      "_id": "liQOgOnRUkmuT35Z",
      "playing": false,
      "pausedTime": null,
      "repeat": false,
      "volume": 0.5,
      "fade": null,
      "sort": 0,
      "flags": {},
      "channel": "music",
      "_key": "!playlists.sounds!uxqHTJ8CQQ3qKQGb.liQOgOnRUkmuT35Z"
    },
    {
      "name": "52 The Gaalsi Fleet Engaged",
      "path": "assets/music/wueste/qwinff_output/52.%20The%20Gaalsi%20Fleet%20Engaged.mp3",
      "_id": "vePH0gTQeewAQq1D",
      "playing": false,
      "pausedTime": null,
      "repeat": false,
      "volume": 0.5,
      "fade": null,
      "sort": 0,
      "flags": {},
      "channel": "music",
      "_key": "!playlists.sounds!uxqHTJ8CQQ3qKQGb.vePH0gTQeewAQq1D"
    },
    {
      "name": "Arraki Dune Ost",
      "path": "assets/music/wueste/qwinff_output/Arraki_Dune_OST.ogg",
      "_id": "uhwgOiC2zrPPudvk",
      "playing": false,
      "pausedTime": null,
      "repeat": false,
      "volume": 0.5,
      "fade": null,
      "sort": 0,
      "flags": {},
      "channel": "music",
      "_key": "!playlists.sounds!uxqHTJ8CQQ3qKQGb.uhwgOiC2zrPPudvk"
    },
    {
      "name": "Belting Ancient Ambient Arabic Middle Eastern Female Vocal Acapella",
      "path": "assets/music/wueste/qwinff_output/Belting_Ancient_Ambient_Arabic_Middle_Eastern_Female_Vocal_Acapella.ogg",
      "_id": "oagzieun7nTztnGC",
      "playing": false,
      "pausedTime": null,
      "repeat": false,
      "volume": 0.5,
      "fade": null,
      "sort": 0,
      "flags": {},
      "channel": "music",
      "_key": "!playlists.sounds!uxqHTJ8CQQ3qKQGb.oagzieun7nTztnGC"
    },
    {
      "name": "Deep Desert Dune Ost",
      "path": "assets/music/wueste/qwinff_output/Deep_Desert_Dune_OST.ogg",
      "_id": "9Z57jn1n4dTnzD4A",
      "playing": false,
      "pausedTime": null,
      "repeat": false,
      "volume": 0.5,
      "fade": null,
      "sort": 0,
      "flags": {},
      "channel": "music",
      "_key": "!playlists.sounds!uxqHTJ8CQQ3qKQGb.9Z57jn1n4dTnzD4A"
    },
    {
      "name": "Gom Jabbar Dune Ost",
      "path": "assets/music/wueste/qwinff_output/Gom_Jabbar_Dune_OST.ogg",
      "_id": "74rsn3LQWKOXFojT",
      "playing": false,
      "pausedTime": null,
      "repeat": false,
      "volume": 0.5,
      "fade": null,
      "sort": 0,
      "flags": {},
      "channel": "music",
      "_key": "!playlists.sounds!uxqHTJ8CQQ3qKQGb.74rsn3LQWKOXFojT"
    },
    {
      "name": "Herald Of The Change Dune Ost",
      "path": "assets/music/wueste/qwinff_output/Herald_of_the_Change_Dune_OST.ogg",
      "_id": "VDJnvWPoOXHGRSut",
      "playing": false,
      "pausedTime": null,
      "repeat": false,
      "volume": 0.5,
      "fade": null,
      "sort": 0,
      "flags": {},
      "channel": "music",
      "_key": "!playlists.sounds!uxqHTJ8CQQ3qKQGb.VDJnvWPoOXHGRSut"
    },
    {
      "name": "Holy War Dune Ost",
      "path": "assets/music/wueste/qwinff_output/Holy_War__Dune_OST.ogg",
      "_id": "VaO1olfgqa7UC7NE",
      "playing": false,
      "pausedTime": null,
      "repeat": false,
      "volume": 0.5,
      "fade": null,
      "sort": 0,
      "flags": {},
      "channel": "music",
      "_key": "!playlists.sounds!uxqHTJ8CQQ3qKQGb.VaO1olfgqa7UC7NE"
    },
    {
      "name": "Homeworld Deserts Of Kharak Ost The Coalition Join In With The Siidim",
      "path": "assets/music/wueste/qwinff_output/Homeworld_Deserts_of_Kharak_OST___The_Coalition_Join_In_With_the_Siidim.ogg",
      "_id": "JLW1GT9UFWQ3kctL",
      "playing": false,
      "pausedTime": null,
      "repeat": false,
      "volume": 0.5,
      "fade": null,
      "sort": 0,
      "flags": {},
      "channel": "music",
      "_key": "!playlists.sounds!uxqHTJ8CQQ3qKQGb.JLW1GT9UFWQ3kctL"
    },
    {
      "name": "Leaving Caladan Dune Ost",
      "path": "assets/music/wueste/qwinff_output/Leaving_Caladan__Dune_OST.ogg",
      "_id": "Whi4nPJYV8NAZzlE",
      "playing": false,
      "pausedTime": null,
      "repeat": false,
      "volume": 0.5,
      "fade": null,
      "sort": 0,
      "flags": {},
      "channel": "music",
      "_key": "!playlists.sounds!uxqHTJ8CQQ3qKQGb.Whi4nPJYV8NAZzlE"
    },
    {
      "name": "My Road Leads Into The Desert Dune Ost",
      "path": "assets/music/wueste/qwinff_output/My_Road_Leads_into_the_Desert__Dune_OST.ogg",
      "_id": "PF7z0rZ4HFiihBVz",
      "playing": false,
      "pausedTime": null,
      "repeat": false,
      "volume": 0.5,
      "fade": null,
      "sort": 0,
      "flags": {},
      "channel": "music",
      "_key": "!playlists.sounds!uxqHTJ8CQQ3qKQGb.PF7z0rZ4HFiihBVz"
    },
    {
      "name": "Paul's Dream Dune Ost",
      "path": "assets/music/wueste/qwinff_output/Paul%27s_Dream__Dune_OST.ogg",
      "_id": "TfL4bBhnUn8qDy3T",
      "playing": false,
      "pausedTime": null,
      "repeat": false,
      "volume": 0.5,
      "fade": null,
      "sort": 0,
      "flags": {},
      "channel": "music",
      "_key": "!playlists.sounds!uxqHTJ8CQQ3qKQGb.TfL4bBhnUn8qDy3T"
    },
    {
      "name": "Ripples In The Sand Dune Ost",
      "path": "assets/music/wueste/qwinff_output/Ripples_in_the_Sand__Dune_OST.ogg",
      "_id": "Zs0uX9oe0oO6G4BQ",
      "playing": false,
      "pausedTime": null,
      "repeat": false,
      "volume": 0.5,
      "fade": null,
      "sort": 0,
      "flags": {},
      "channel": "music",
      "_key": "!playlists.sounds!uxqHTJ8CQQ3qKQGb.Zs0uX9oe0oO6G4BQ"
    },
    {
      "name": "Stillsuits Dune Ost",
      "path": "assets/music/wueste/qwinff_output/Stillsuits__Dune_OST.ogg",
      "_id": "6uAJbhSDT7IiIK2N",
      "playing": false,
      "pausedTime": null,
      "repeat": false,
      "volume": 0.5,
      "fade": null,
      "sort": 0,
      "flags": {},
      "channel": "music",
      "_key": "!playlists.sounds!uxqHTJ8CQQ3qKQGb.6uAJbhSDT7IiIK2N"
    },
    {
      "name": "Stronghold Crusader Soundtrack A Strong Spice 128kbit Aac",
      "path": "assets/music/wueste/qwinff_output/Stronghold_Crusader_Soundtrack__A_Strong_Spice__128kbit_AAC_.ogg",
      "_id": "kcxLsbs1x6F8TpU9",
      "playing": false,
      "pausedTime": null,
      "repeat": false,
      "volume": 0.5,
      "fade": null,
      "sort": 0,
      "flags": {},
      "channel": "music",
      "_key": "!playlists.sounds!uxqHTJ8CQQ3qKQGb.kcxLsbs1x6F8TpU9"
    },
    {
      "name": "Stronghold Crusader Soundtrack Caravan Ambient 128kbit Aac",
      "path": "assets/music/wueste/qwinff_output/Stronghold_Crusader_Soundtrack__Caravan_Ambient__128kbit_AAC_.ogg",
      "_id": "VoX89PH5CGIafZtz",
      "playing": false,
      "pausedTime": null,
      "repeat": false,
      "volume": 0.5,
      "fade": null,
      "sort": 0,
      "flags": {},
      "channel": "music",
      "_key": "!playlists.sounds!uxqHTJ8CQQ3qKQGb.VoX89PH5CGIafZtz"
    },
    {
      "name": "Stronghold Crusader Soundtrack Caravan 128kbit Aac",
      "path": "assets/music/wueste/qwinff_output/Stronghold_Crusader_Soundtrack__Caravan__128kbit_AAC_.ogg",
      "_id": "ZLUnSP8Ue2enPtBU",
      "playing": false,
      "pausedTime": null,
      "repeat": false,
      "volume": 0.5,
      "fade": null,
      "sort": 0,
      "flags": {},
      "channel": "music",
      "_key": "!playlists.sounds!uxqHTJ8CQQ3qKQGb.ZLUnSP8Ue2enPtBU"
    },
    {
      "name": "Stronghold Crusader Soundtrack Crusader Solo 128kbit Aac",
      "path": "assets/music/wueste/qwinff_output/Stronghold_Crusader_Soundtrack__Crusader_solo__128kbit_AAC_.ogg",
      "_id": "BIE7BtzAiHUYe1Tj",
      "playing": false,
      "pausedTime": null,
      "repeat": false,
      "volume": 0.5,
      "fade": null,
      "sort": 0,
      "flags": {},
      "channel": "music",
      "_key": "!playlists.sounds!uxqHTJ8CQQ3qKQGb.BIE7BtzAiHUYe1Tj"
    },
    {
      "name": "Stronghold Crusader Soundtrack Crusader 128kbit Aac",
      "path": "assets/music/wueste/qwinff_output/Stronghold_Crusader_Soundtrack__Crusader__128kbit_AAC_.ogg",
      "_id": "rJmZFKWk0Fs1l1Ce",
      "playing": false,
      "pausedTime": null,
      "repeat": false,
      "volume": 0.5,
      "fade": null,
      "sort": 0,
      "flags": {},
      "channel": "music",
      "_key": "!playlists.sounds!uxqHTJ8CQQ3qKQGb.rJmZFKWk0Fs1l1Ce"
    },
    {
      "name": "Stronghold Crusader Soundtrack Dar Meshq 128kbit Aac",
      "path": "assets/music/wueste/qwinff_output/Stronghold_Crusader_Soundtrack__Dar_Meshq__128kbit_AAC_.ogg",
      "_id": "0VnHTytYEOtCbhvV",
      "playing": false,
      "pausedTime": null,
      "repeat": false,
      "volume": 0.5,
      "fade": null,
      "sort": 0,
      "flags": {},
      "channel": "music",
      "_key": "!playlists.sounds!uxqHTJ8CQQ3qKQGb.0VnHTytYEOtCbhvV"
    },
    {
      "name": "Stronghold Crusader Soundtrack Gorn With The Wind 128kbit Aac",
      "path": "assets/music/wueste/qwinff_output/Stronghold_Crusader_Soundtrack__Gorn_with_the_Wind__128kbit_AAC_.ogg",
      "_id": "SHUBsgMJCD9BCLCa",
      "playing": false,
      "pausedTime": null,
      "repeat": false,
      "volume": 0.5,
      "fade": null,
      "sort": 0,
      "flags": {},
      "channel": "music",
      "_key": "!playlists.sounds!uxqHTJ8CQQ3qKQGb.SHUBsgMJCD9BCLCa"
    },
    {
      "name": "Stronghold Crusader Soundtrack Oudunnit 128kbit Aac",
      "path": "assets/music/wueste/qwinff_output/Stronghold_Crusader_Soundtrack__Oudunnit__128kbit_AAC_.ogg",
      "_id": "RI4UJs8Dw5tE5WhU",
      "playing": false,
      "pausedTime": null,
      "repeat": false,
      "volume": 0.5,
      "fade": null,
      "sort": 0,
      "flags": {},
      "channel": "music",
      "_key": "!playlists.sounds!uxqHTJ8CQQ3qKQGb.RI4UJs8Dw5tE5WhU"
    },
    {
      "name": "Stronghold Crusader Soundtrack Sandal Maker 128kbit Aac",
      "path": "assets/music/wueste/qwinff_output/Stronghold_Crusader_Soundtrack__Sandal_Maker__128kbit_AAC_.ogg",
      "_id": "hQi9XnZ8D0A7nuqb",
      "playing": false,
      "pausedTime": null,
      "repeat": false,
      "volume": 0.5,
      "fade": null,
      "sort": 0,
      "flags": {},
      "channel": "music",
      "_key": "!playlists.sounds!uxqHTJ8CQQ3qKQGb.hQi9XnZ8D0A7nuqb"
    },
    {
      "name": "Stronghold Crusader Soundtrack The Last Drop 128kbit Aac",
      "path": "assets/music/wueste/qwinff_output/Stronghold_Crusader_Soundtrack__The_Last_Drop__128kbit_AAC_.ogg",
      "_id": "34RYd2iPhZsnlybv",
      "playing": false,
      "pausedTime": null,
      "repeat": false,
      "volume": 0.5,
      "fade": null,
      "sort": 0,
      "flags": {},
      "channel": "music",
      "_key": "!playlists.sounds!uxqHTJ8CQQ3qKQGb.34RYd2iPhZsnlybv"
    },
    {
      "name": "Stronghold Crusader Soundtrack Trancefusion 128kbit Aac",
      "path": "assets/music/wueste/qwinff_output/Stronghold_Crusader_Soundtrack__Trancefusion__128kbit_AAC_.ogg",
      "_id": "UcguEkiDZpri2B9w",
      "playing": false,
      "pausedTime": null,
      "repeat": false,
      "volume": 0.5,
      "fade": null,
      "sort": 0,
      "flags": {},
      "channel": "music",
      "_key": "!playlists.sounds!uxqHTJ8CQQ3qKQGb.UcguEkiDZpri2B9w"
    },
    {
      "name": "The Fall Dune Ost",
      "path": "assets/music/wueste/qwinff_output/The_Fall_Dune_OST.ogg",
      "_id": "tba5fQopYutGqx7b",
      "playing": false,
      "pausedTime": null,
      "repeat": false,
      "volume": 0.5,
      "fade": null,
      "sort": 0,
      "flags": {},
      "channel": "music",
      "_key": "!playlists.sounds!uxqHTJ8CQQ3qKQGb.tba5fQopYutGqx7b"
    },
    {
      "name": "Vaygr Battle Theme Alternate",
      "path": "assets/music/wueste/qwinff_output/Vaygr_Battle_Theme__Alternate_.ogg",
      "_id": "3QOaQSWVLz1njUj4",
      "playing": false,
      "pausedTime": null,
      "repeat": false,
      "volume": 0.5,
      "fade": null,
      "sort": 0,
      "flags": {},
      "channel": "music",
      "_key": "!playlists.sounds!uxqHTJ8CQQ3qKQGb.3QOaQSWVLz1njUj4"
    }
  ],
  "mode": 0,
  "playing": false,
  "fade": null,
  "folder": "Q6CxjFYQvGxq22AH",
  "sorting": "a",
  "seed": null,
  "ownership": {
    "default": 0,
    "OkB1KdnOuvyQ8qU2": 3
  },
  "flags": {
    "core": {}
  },
  "_stats": {
    "systemId": "dsa5",
    "systemVersion": "5.7.4",
    "coreVersion": "12.331",
    "createdTime": 1719472970936,
    "modifiedTime": 1719473037628,
    "lastModifiedBy": "OkB1KdnOuvyQ8qU2",
    "compendiumSource": null,
    "duplicateSource": null
  },
  "description": "",
  "_id": "uxqHTJ8CQQ3qKQGb",
  "sort": 0,
  "channel": "music",
  "_key": "!playlists!uxqHTJ8CQQ3qKQGb"
}
