{
  "name": "Klammer des Molochen",
  "type": "anatomy",
  "img": "icons/magic/life/heart-cross-strong-flame-green.webp",
  "system": {
    "creatureClass": {
      "value": "all"
    },
    "traitType": {
      "value": "activeability"
    },
    "effect": {
      "value": ""
    },
    "mountEffect": {
      "value": ""
    },
    "effects": {
      "effectKey": "",
      "onlyMessage": false,
      "effect": ";",
      "damageValue": "",
      "duration": "",
      "effectValue": ""
    },
    "guidevalue": {
      "value": "-"
    },
    "difficulty": {
      "value": null
    },
    "structure": {
      "hasStructure": false
    },
    "selectable": {
      "value": false,
      "cost": 3
    },
    "attributes": {
      "value": "mu"
    },
    "onactor": {
      "value": false
    },
    "actioncost": {
      "value": null,
      "type": "atactions"
    },
    "description": {
      "value": "<p>So lange er geklammert ist, wird jeder Schaden den der Klammernde erh&auml;lt auf den Geklammerten &uuml;bertragen.</p>"
    }
  },
  "effects": [],
  "folder": "BWfw8gIrXVOgFqW5",
  "ownership": {
    "default": 0,
    "k2irxkER7dd27yKp": 3
  },
  "flags": {
    "core": {}
  },
  "_stats": {
    "systemId": "dsa5",
    "systemVersion": "5.7.4",
    "coreVersion": "12.331",
    "createdTime": 1721460318063,
    "modifiedTime": 1726331219368,
    "lastModifiedBy": "k2irxkER7dd27yKp",
    "compendiumSource": null,
    "duplicateSource": null
  },
  "_id": "MePMdTy9nQR4jaPR",
  "sort": 800000,
  "_key": "!items!MePMdTy9nQR4jaPR"
}
